polymorph/__init__.py
polymorph/converter.py
polymorph/ftype.py
polymorph/interceptor.py
polymorph/packet.py
polymorph/template.py
polymorph/tfield.py
polymorph/tgenerator.py
polymorph/tlayer.py
polymorph/tlist.py
polymorph/utils.py
polymorph/UI/__init__.py
polymorph/UI/banners.py
polymorph/UI/command_parser.py
polymorph/UI/fieldinterface.py
polymorph/UI/interface.py
polymorph/UI/layerinterface.py
polymorph/UI/maininterface.py
polymorph/UI/templateinterface.py
polymorph/UI/tlistinterface.py
polymorph/functions/__init__.py
polymorph/spoofs/__init__.py
polymorph/spoofs/arpspoof.py
polymorph/spoofs/poison.py
polymorph-2.0.6.data/scripts/polymorph
polymorph-2.0.6.dist-info/LICENSE
polymorph-2.0.6.dist-info/METADATA
polymorph-2.0.6.dist-info/WHEEL
polymorph-2.0.6.dist-info/top_level.txt
polymorph-2.0.6.dist-info/RECORD
